leopy/__about__.py
leopy/__init__.py
leopy/convolution.py
leopy/integrate.py
leopy/likelihood.py
leopy/misc.py
leopy/observation.py
leopy/stats.py
leopy/test/__init__.py
leopy/test/conftest.py
leopy/test/test_convolution.py
leopy/test/test_likelihood.py
leopy_stat-0.9.3.dist-info/LICENSE.txt
leopy_stat-0.9.3.dist-info/METADATA
leopy_stat-0.9.3.dist-info/WHEEL
leopy_stat-0.9.3.dist-info/top_level.txt
leopy_stat-0.9.3.dist-info/RECORD
