Metadata-Version: 2.1
Name: leopy-stat
Version: 0.9.3
Summary: Likelihood Estimation for Observational data with Python
Home-page: http://github.com/rfeldmann/leopy
Author: Robert Feldmann
Author-email: RobertFeldmann@gmx.de
Maintainer: Robert Feldmann
Maintainer-email: RobertFeldmann@gmx.de
License: GNU GPLv3
Keywords: statistics likelihood probability
Platform: UNKNOWN
Classifier: Development Status :: 4 - Beta
Classifier: License :: OSI Approved :: GNU General Public License v3 (GPLv3)
Classifier: Programming Language :: Python :: 3
Classifier: Topic :: Scientific/Engineering :: Mathematics
Requires-Python: >=3.5
Requires-Dist: pandas (>=0.24.0)
Requires-Dist: scipy (>=1.3.0)
Requires-Dist: numpy
Requires-Dist: sphinx
Requires-Dist: sphinx-rtd-theme
Provides-Extra: mpi
Requires-Dist: schwimmbad ; extra == 'mpi'
Requires-Dist: mpi4py ; extra == 'mpi'
Provides-Extra: multiprocessing
Requires-Dist: schwimmbad ; extra == 'multiprocessing'
